sageworks/__init__.py
sageworks/algorithms/__init__.py
sageworks/algorithms/dataframe/Readme.md
sageworks/algorithms/dataframe/__init__.py
sageworks/algorithms/dataframe/aggregation.py
sageworks/algorithms/dataframe/data_source_eda.py
sageworks/algorithms/dataframe/dimensionality_reduction.py
sageworks/algorithms/dataframe/feature_resolution.py
sageworks/algorithms/dataframe/feature_space_proximity.py
sageworks/algorithms/dataframe/feature_spider.py
sageworks/algorithms/dataframe/knn_spider_deprecated.py
sageworks/algorithms/dataframe/quantile_regression.py
sageworks/algorithms/dataframe/residuals_calculator.py
sageworks/algorithms/dataframe/row_tagger.py
sageworks/algorithms/dataframe/target_gradients.py
sageworks/algorithms/graph/__init__.py
sageworks/algorithms/graph/heavy/Readme.md
sageworks/algorithms/graph/light/Readme.md
sageworks/algorithms/graph/light/__init__.py
sageworks/algorithms/graph/light/proximity_graph.py
sageworks/algorithms/spark/Readme.md
sageworks/algorithms/sql/Readme.md
sageworks/algorithms/sql/__init__.py
sageworks/algorithms/sql/column_stats.py
sageworks/algorithms/sql/correlations.py
sageworks/algorithms/sql/descriptive_stats.py
sageworks/algorithms/sql/outliers.py
sageworks/algorithms/sql/sample_rows.py
sageworks/algorithms/sql/value_counts.py
sageworks/api/__init__.py
sageworks/api/data_source.py
sageworks/api/df_store.py
sageworks/api/endpoint.py
sageworks/api/feature_set.py
sageworks/api/meta.py
sageworks/api/model.py
sageworks/api/monitor.py
sageworks/api/parameter_store.py
sageworks/api/pipeline.py
sageworks/cached/__init__.py
sageworks/cached/cached_data_source.py
sageworks/cached/cached_endpoint.py
sageworks/cached/cached_feature_set.py
sageworks/cached/cached_meta.py
sageworks/cached/cached_model.py
sageworks/cached/cached_pipeline.py
sageworks/core/__init__.py
sageworks/core/artifacts/__init__.py
sageworks/core/artifacts/artifact.py
sageworks/core/artifacts/athena_source.py
sageworks/core/artifacts/cached_artifact_mixin.py
sageworks-0.8.89.dist-info/LICENSE
sageworks-0.8.89.dist-info/METADATA
sageworks-0.8.89.dist-info/WHEEL
sageworks-0.8.89.dist-info/entry_points.txt
sageworks-0.8.89.dist-info/top_level.txt
sageworks-0.8.89.dist-info/RECORD
