Metadata-Version: 2.2
Name: sageworks
Version: 0.8.89
Summary: SageWorks: A Dashboard and Python API for creating and deploying AWS SageMaker Model Pipelines
Author-email: SuperCowPowers LLC <support@supercowpowers.com>
License: MIT
Project-URL: Homepage, https://github.com/SuperCowPowers/sageworks
Keywords: SageMaker,Machine Learning,AWS,Python,Utilities
Classifier: Development Status :: 4 - Beta
Classifier: License :: OSI Approved :: MIT License
Classifier: Programming Language :: Python :: 3.10
Classifier: Programming Language :: Python :: 3.11
Classifier: Programming Language :: Python :: 3.12
Classifier: Topic :: Scientific/Engineering
Requires-Python: >=3.9
License-File: LICENSE
Requires-Dist: boto3>=1.28.76
Requires-Dist: botocore>=1.31.76
Requires-Dist: redis>=5.0.1
Requires-Dist: numpy>=1.26.4
Requires-Dist: pandas>=2.2.1
Requires-Dist: awswrangler>=3.4.0
Requires-Dist: sagemaker>=2.143
Requires-Dist: cryptography>=42.0.5
Requires-Dist: ipython>=8.17.2
Requires-Dist: pyreadline3; sys_platform == "win32"
Requires-Dist: xgboost>=2.0.3
Requires-Dist: scikit-learn<=1.5.2,>=1.4.2
Requires-Dist: joblib>=1.3.2
Requires-Dist: requests>=2.26.0
Provides-Extra: ml-tools
Requires-Dist: shap>=0.46.0; extra == "ml-tools"
Requires-Dist: networkx>=3.2; extra == "ml-tools"
Provides-Extra: chem
Requires-Dist: rdkit>=2023.9.1; extra == "chem"
Requires-Dist: mordredcommunity>=2.0; extra == "chem"
Provides-Extra: ui
Requires-Dist: plotly>=5.18.0; extra == "ui"
Requires-Dist: dash>=2.16.1; extra == "ui"
Requires-Dist: dash-bootstrap-components>=1.6.0; extra == "ui"
Requires-Dist: dash-bootstrap-templates>=1.3.0; extra == "ui"
Requires-Dist: dash_ag_grid; extra == "ui"
Requires-Dist: tabulate>=0.9.0; extra == "ui"
Requires-Dist: matplotlib>=3.9.2; extra == "ui"
Provides-Extra: dev
Requires-Dist: pytest; extra == "dev"
Requires-Dist: pytest-sugar; extra == "dev"
Requires-Dist: coverage; extra == "dev"
Requires-Dist: pytest-cov; extra == "dev"
Requires-Dist: flake8; extra == "dev"
Requires-Dist: black; extra == "dev"
Provides-Extra: all
Requires-Dist: shap>=0.46.0; extra == "all"
Requires-Dist: networkx>=3.2; extra == "all"
Requires-Dist: rdkit>=2023.9.1; extra == "all"
Requires-Dist: mordredcommunity>=2.0; extra == "all"
Requires-Dist: plotly>=5.18.0; extra == "all"
Requires-Dist: dash>=2.16.1; extra == "all"
Requires-Dist: dash-bootstrap-components>=1.6.0; extra == "all"
Requires-Dist: dash-bootstrap-templates>=1.3.0; extra == "all"
Requires-Dist: dash_ag_grid; extra == "all"
Requires-Dist: tabulate>=0.9.0; extra == "all"
Requires-Dist: pytest; extra == "all"
Requires-Dist: pytest-sugar; extra == "all"
Requires-Dist: coverage; extra == "all"
Requires-Dist: pytest-cov; extra == "all"
Requires-Dist: flake8; extra == "all"
Requires-Dist: black; extra == "all"
